sql_splitter/__init__.py
sql_splitter/core/__init__.py
sql_splitter/core/ast_nodes.py
sql_splitter/core/content_extractor.py
sql_splitter/core/cte_handler.py
sql_splitter/core/join_handler.py
sql_splitter/core/sql_normalizer_mysql.py
sql_splitter/core/sql_parser_ast_v6_0.py
sql_splitter/core/sql_parser_wrapper.py
sql_splitter/core/sql_tokenizer.py
sql_splitter/core/table_extractor.py
sql_splitter-6.1.0.dist-info/licenses/LICENSE
sql_splitter-6.1.0.dist-info/METADATA
sql_splitter-6.1.0.dist-info/WHEEL
sql_splitter-6.1.0.dist-info/entry_points.txt
sql_splitter-6.1.0.dist-info/top_level.txt
sql_splitter-6.1.0.dist-info/RECORD
