Metadata-Version: 2.4
Name: sql-splitter
Version: 6.1.0
Summary: Advanced MySQL SQL Parser with Visualization Component Support
Author-email: SQL Splitter Team <contact@sqlsplitter.dev>
License-Expression: MIT
Project-URL: Homepage, https://github.com/alexkwok22/sql-splitter
Project-URL: Documentation, https://github.com/alexkwok22/sql-splitter/blob/main/docs/
Project-URL: Repository, https://github.com/alexkwok22/sql-splitter
Project-URL: Bug Reports, https://github.com/alexkwok22/sql-splitter/issues
Keywords: sql,parser,mysql,visualization,ast,database,query,analysis
Classifier: Development Status :: 5 - Production/Stable
Classifier: Intended Audience :: Developers
Classifier: Topic :: Software Development :: Libraries :: Python Modules
Classifier: Topic :: Database
Classifier: Topic :: Text Processing :: Linguistic
Classifier: Programming Language :: Python :: 3
Classifier: Programming Language :: Python :: 3.7
Classifier: Programming Language :: Python :: 3.8
Classifier: Programming Language :: Python :: 3.9
Classifier: Programming Language :: Python :: 3.10
Classifier: Programming Language :: Python :: 3.11
Requires-Python: >=3.7
License-File: LICENSE
Provides-Extra: dev
Requires-Dist: pytest>=6.0; extra == "dev"
Requires-Dist: pytest-cov; extra == "dev"
Requires-Dist: black; extra == "dev"
Requires-Dist: flake8; extra == "dev"
Provides-Extra: test
Requires-Dist: pytest>=6.0; extra == "test"
Requires-Dist: pytest-cov; extra == "test"
Dynamic: license-file
